balance_service/__init__.py
balance_service/interfaces/__init__.py
balance_service/interfaces/boto_s3.py
balance_service/interfaces/nubank.py
balance_service/repositories/__init__.py
balance_service/repositories/bank.py
balance_service/repositories/user.py
balance_service-0.0.14.dist-info/METADATA
balance_service-0.0.14.dist-info/WHEEL
balance_service-0.0.14.dist-info/top_level.txt
balance_service-0.0.14.dist-info/RECORD
