Metadata-Version: 2.1
Name: balance-service
Version: 0.0.14
Summary: Objetivos:
Home-page: https://pypi.org/project/balance-service
Author: Calenzo
Author-email: calenzodevs@gmail.com
License: MIT License
Classifier: Programming Language :: Python :: 3.7
Classifier: Programming Language :: Python :: 3.8
Classifier: Natural Language :: English
Classifier: License :: OSI Approved :: MIT License
Classifier: Operating System :: OS Independent
Requires-Dist: balance-domain (==0.1.36)
